setup.py
ohashi/__init__.py
ohashi/backends.py
ohashi/constants.py
ohashi/pkgmeta.py
ohashi/shortcuts.py
ohashi.egg-info/PKG-INFO
ohashi.egg-info/SOURCES.txt
ohashi.egg-info/dependency_links.txt
ohashi.egg-info/not-zip-safe
ohashi.egg-info/requires.txt
ohashi.egg-info/top_level.txt
ohashi/db/__init__.py
ohashi/db/models/__init__.py
ohashi/db/models/fields/__init__.py
ohashi/db/models/fields/birthdays.py
ohashi/db/models/managers/__init__.py
ohashi/db/models/managers/birthdays.py
ohashi/redis/__init__.py
ohashi/redis/utils.py