Metadata-Version: 1.1
Name: ohashi
Version: 0.2.9
Summary: Yet another opinionated utilities kit for Django projects.
Home-page: http://github.com/hello-base/ohashi
Author: Bryan Veloso
Author-email: bryan@hello-base.com
License: BSD
Platform: UNKNOWN
Classifier: Development Status :: 3 - Alpha
Classifier: Environment :: Web Environment
Classifier: Framework :: Django
Classifier: Intended Audience :: Developers
Classifier: License :: OSI Approved :: BSD License
Classifier: Operating System :: OS Independent
Classifier: Programming Language :: Python :: 2.7
Classifier: Topic :: Utilities
